rinoh_typeface_dejavuserif/AUTHORS
rinoh_typeface_dejavuserif/BUGS
rinoh_typeface_dejavuserif/DejaVuSerif-Bold.ttf
rinoh_typeface_dejavuserif/DejaVuSerif-BoldItalic.ttf
rinoh_typeface_dejavuserif/DejaVuSerif-Italic.ttf
rinoh_typeface_dejavuserif/DejaVuSerif.ttf
rinoh_typeface_dejavuserif/DejaVuSerifCondensed-Bold.ttf
rinoh_typeface_dejavuserif/DejaVuSerifCondensed-BoldItalic.ttf
rinoh_typeface_dejavuserif/DejaVuSerifCondensed-Italic.ttf
rinoh_typeface_dejavuserif/DejaVuSerifCondensed.ttf
rinoh_typeface_dejavuserif/LICENSE
rinoh_typeface_dejavuserif/NEWS
rinoh_typeface_dejavuserif/README.md
rinoh_typeface_dejavuserif/__init__.py
rinoh_typeface_dejavuserif/langcover.txt
rinoh_typeface_dejavuserif/status.txt
rinoh_typeface_dejavuserif/unicover.txt
rinoh_typeface_dejavuserif-0.1.3.dist-info/METADATA
rinoh_typeface_dejavuserif-0.1.3.dist-info/WHEEL
rinoh_typeface_dejavuserif-0.1.3.dist-info/entry_points.txt
rinoh_typeface_dejavuserif-0.1.3.dist-info/top_level.txt
rinoh_typeface_dejavuserif-0.1.3.dist-info/RECORD
