Metadata-Version: 1.1
Name: rinoh-typeface-dejavuserif
Version: 0.1.3
Summary: DejaVu Serif typeface
Home-page: https://github.com/brechtm/rinoh-typeface-dejavuserif
Author: Brecht Machiels
Author-email: brecht@mos6581.org
License: Bitstream Vera Fonts Copyright, Arev Fonts Copyright, Public Domain
Keywords: opentype font
Platform: UNKNOWN
Classifier: Intended Audience :: Developers
Classifier: Intended Audience :: End Users/Desktop
Classifier: Operating System :: OS Independent
Classifier: Programming Language :: Python
Classifier: Programming Language :: Python :: 3
Classifier: Topic :: Text Processing :: Fonts
